urimai/__init__.py
urimai/config.py
urimai/main.py
urimai/setup_wizard.py
urimai/agents/__init__.py
urimai/agents/analysis_agent.py
urimai/agents/enrichment_agent.py
urimai/agents/quality_generation_agent.py
urimai/agents/quality_interpreter_agent.py
urimai/agents/query_agent.py
urimai/agents/query_planner_agent.py
urimai/agents/role_classification_agent.py
urimai/agents/schema_context_agent.py
urimai/agents/schema_inference_agent.py
urimai/agents/schema_selection_agent.py
urimai/core/__init__.py
urimai/core/chat_session.py
urimai/core/context_manager.py
urimai/core/csv_ingestion.py
urimai/core/db_manager.py
urimai/core/export.py
urimai/core/interactive.py
urimai/core/plan_executor.py
urimai/core/query_executor.py
urimai/core/schema_extractor.py
urimai/core/insights/__init__.py
urimai/core/profiling/__init__.py
urimai/core/profiling/column_profiler.py
urimai/core/profiling/role_classifier.py
urimai/core/quality/__init__.py
urimai/core/quality/completeness_check.py
urimai/core/quality/consistency_check.py
urimai/core/quality/uniqueness_check.py
urimai/core/quality/validity_check.py
urimai/storage/__init__.py
urimai/storage/metadata_store.py
urimai/storage/models.py
urimai/utils/__init__.py
urimai/utils/display.py
urimai/utils/llm.py
urimai-0.1.5.dist-info/licenses/LICENSE
urimai-0.1.5.dist-info/METADATA
urimai-0.1.5.dist-info/WHEEL
urimai-0.1.5.dist-info/entry_points.txt
urimai-0.1.5.dist-info/top_level.txt
urimai-0.1.5.dist-info/RECORD
