Metadata-Version: 2.4
Name: urimai
Version: 0.1.5
Summary: AI-powered SQL answer engine - ask questions about your databases
Author: Shiva
License: Elastic License 2.0 (ELv2)
Project-URL: Homepage, https://github.com/shivakharbanda/urimAI
Project-URL: Source, https://github.com/shivakharbanda/urimAI
Keywords: sql,ai,llm,database,natural-language,query
Classifier: Development Status :: 3 - Alpha
Classifier: Intended Audience :: Developers
Classifier: Programming Language :: Python :: 3
Classifier: Programming Language :: Python :: 3.11
Classifier: Programming Language :: Python :: 3.12
Classifier: Programming Language :: Python :: 3.13
Classifier: Topic :: Database
Requires-Python: >=3.11
License-File: LICENSE
Requires-Dist: dq-db-manager>=0.2.0
Requires-Dist: pydantic>=2.12.3
Requires-Dist: pydantic-ai>=0.0.14
Requires-Dist: typer>=0.12.0
Requires-Dist: rich>=13.0.0
Requires-Dist: keyring>=25.0.0
Requires-Dist: tomli-w>=1.0.0
Requires-Dist: aiosqlite>=0.20.0
Requires-Dist: prompt-toolkit>=3.0.0
Requires-Dist: numpy>=2.3.4
Requires-Dist: scipy>=1.16.3
Requires-Dist: pandas>=2.0.0
Requires-Dist: openai>=1.0.0
Requires-Dist: openpyxl>=3.1.0
Provides-Extra: docs
Requires-Dist: sphinx>=8.1.0; extra == "docs"
Requires-Dist: sphinx-autodoc-typehints>=2.5.0; extra == "docs"
Requires-Dist: furo>=2024.1.29; extra == "docs"
Requires-Dist: myst-parser>=4.0.0; extra == "docs"
Dynamic: license-file
